{
    "user": [
        {
            "uid": "100022089907330",
            "countmsg": 29
        },
        {
            "uid": "100033751985199",
            "countmsg": 19
        },
        {
            "uid": "100083235279354",
            "countmsg": 6
        },
        {
            "uid": "100074359366206",
            "countmsg": 3
        },
        {
            "uid": "100079859798851",
            "countmsg": 131
        },
        {
            "uid": "100054416075122",
            "countmsg": 9
        },
        {
            "uid": "757649544",
            "countmsg": 3
        },
        {
            "uid": "100077295775375",
            "countmsg": 4
        }
    ]
}