{
    "user": [
        {
            "uid": "100089805249898",
            "countmsg": 25
        },
        {
            "uid": "100046612876043",
            "countmsg": 0
        },
        {
            "uid": "100079859798851",
            "countmsg": 343
        },
        {
            "uid": "100078826673805",
            "countmsg": 2
        },
        {
            "uid": "100080069919929",
            "countmsg": 21
        },
        {
            "uid": "100050511061402",
            "countmsg": 29
        },
        {
            "uid": "100086468590711",
            "countmsg": 11
        },
        {
            "uid": "100040248379702",
            "countmsg": 22
        },
        {
            "uid": "100053745639742",
            "countmsg": 4
        },
        {
            "uid": "100082897485998",
            "countmsg": 7
        },
        {
            "uid": "100076147081058",
            "countmsg": 4
        },
        {
            "uid": "100057659296318",
            "countmsg": 17
        },
        {
            "uid": "100074392909474",
            "countmsg": 1
        },
        {
            "uid": "100060357320241",
            "countmsg": 5
        },
        {
            "uid": "100081911185619",
            "countmsg": 0
        },
        {
            "uid": "100070720701814",
            "countmsg": 35
        },
        {
            "uid": "100075715147754",
            "countmsg": 0
        },
        {
            "uid": "100075137192555",
            "countmsg": 0
        },
        {
            "uid": "100042454980542",
            "countmsg": 19
        },
        {
            "uid": "100078504375179",
            "countmsg": 1
        }
    ]
}