{
    "user": [
        {
            "uid": "100075628129295",
            "countmsg": 3
        },
        {
            "uid": "100071661426729",
            "countmsg": 3
        },
        {
            "uid": "100076142093986",
            "countmsg": 33
        },
        {
            "uid": "100050053005171",
            "countmsg": 36
        },
        {
            "uid": "100085099234547",
            "countmsg": 24
        },
        {
            "uid": "100074392909474",
            "countmsg": 9
        },
        {
            "uid": "100064079924569",
            "countmsg": 7
        },
        {
            "uid": "100070090911392",
            "countmsg": 3
        },
        {
            "uid": "100072849158907",
            "countmsg": 1
        },
        {
            "uid": "100076310994943",
            "countmsg": 1
        },
        {
            "uid": "100086415765506",
            "countmsg": 2
        },
        {
            "uid": "100072960144751",
            "countmsg": 3
        },
        {
            "uid": "100054416075122",
            "countmsg": 30
        },
        {
            "uid": "100057280964421",
            "countmsg": 6
        },
        {
            "uid": "100073483576924",
            "countmsg": 0
        },
        {
            "uid": "100075632650470",
            "countmsg": 0
        },
        {
            "uid": "100025413919609",
            "countmsg": 4
        },
        {
            "uid": "100084522131417",
            "countmsg": 2
        },
        {
            "uid": "100081209323030",
            "countmsg": 1
        },
        {
            "uid": "100074367680814",
            "countmsg": 1
        }
    ]
}