{
    "user": [
        {
            "uid": "100069367614115",
            "countmsg": 575
        },
        {
            "uid": "100087595727224",
            "countmsg": 206
        },
        {
            "uid": "100080643360343",
            "countmsg": 226
        },
        {
            "uid": "100062557572179",
            "countmsg": 23
        },
        {
            "uid": "100072915175144",
            "countmsg": 56
        },
        {
            "uid": "100071016991372",
            "countmsg": 76
        }
    ]
}