{
    "user": [
        {
            "uid": "100078717829755",
            "countmsg": 29
        },
        {
            "uid": "100070159519360",
            "countmsg": 103
        },
        {
            "uid": "100054712301205",
            "countmsg": 13
        },
        {
            "uid": "100085887007971",
            "countmsg": 11
        },
        {
            "uid": "100084657540140",
            "countmsg": 12
        },
        {
            "uid": "100001447471057",
            "countmsg": 52
        },
        {
            "uid": "100088721001065",
            "countmsg": 42
        },
        {
            "uid": "100082074985853",
            "countmsg": 42
        },
        {
            "uid": "1041274837",
            "countmsg": 2
        },
        {
            "uid": "100021878103574",
            "countmsg": 6
        },
        {
            "uid": "636593513",
            "countmsg": 0
        },
        {
            "uid": "100016622043247",
            "countmsg": 1
        },
        {
            "uid": "607693421",
            "countmsg": 7
        }
    ]
}