{
    "user": [
        {
            "uid": "100074030268329",
            "countmsg": 45
        },
        {
            "uid": "100087946637555",
            "countmsg": 126
        },
        {
            "uid": "100067731976878",
            "countmsg": 234
        },
        {
            "uid": "100054416075122",
            "countmsg": 89
        },
        {
            "uid": "100078004367335",
            "countmsg": 33
        },
        {
            "uid": "100083503856164",
            "countmsg": 12
        },
        {
            "uid": "100090019110966",
            "countmsg": 1
        },
        {
            "uid": "100088815016051",
            "countmsg": 25
        },
        {
            "uid": "1578274342",
            "countmsg": 18
        },
        {
            "uid": "100040461800609",
            "countmsg": 75
        },
        {
            "uid": "100083954395951",
            "countmsg": 11
        },
        {
            "uid": "100065430669235",
            "countmsg": 3
        },
        {
            "uid": "100082145035733",
            "countmsg": 10
        },
        {
            "uid": "100047851953715",
            "countmsg": 0
        }
    ]
}